rquge_score/__init__.py
rquge_score/scorer.py
rquge_score_cli/__init__.py
rquge_score_cli/scorer_cli.py
rquge-0.3.dist-info/LICENSE
rquge-0.3.dist-info/METADATA
rquge-0.3.dist-info/WHEEL
rquge-0.3.dist-info/entry_points.txt
rquge-0.3.dist-info/top_level.txt
rquge-0.3.dist-info/RECORD
