Metadata-Version: 2.1
Name: rquge
Version: 0.3
Summary: PyTorch implementation of RQUGE score
Home-page: https://github.com/alirezamshi/RQUGE
Author: Alireza Mohammadshahi*, Thomas Scialom, Majid Yazdani, Pouya Yanki, Angela Fan, James Henderson, Marzieh Saeidi
Author-email: alireza.msh1373@gmail.com
License: MIT
Keywords: BERT NLP deep learning QG QA metric
Classifier: Intended Audience :: Science/Research
Classifier: License :: OSI Approved :: MIT License
Classifier: Programming Language :: Python :: 3
Classifier: Topic :: Scientific/Engineering :: Artificial Intelligence
Requires-Python: >=3.7
License-File: LICENSE
Requires-Dist: torch
Requires-Dist: transformers
Requires-Dist: numpy
Requires-Dist: sentencepiece
